pytorch-model-parser/__init__.py
pytorch-model-parser/parser.py
pytorch_model_parser/__init__.py
pytorch_model_parser/parser.py
pytorch_model_parser-0.1.0.dist-info/LICENSE
pytorch_model_parser-0.1.0.dist-info/METADATA
pytorch_model_parser-0.1.0.dist-info/WHEEL
pytorch_model_parser-0.1.0.dist-info/top_level.txt
pytorch_model_parser-0.1.0.dist-info/RECORD
