Metadata-Version: 2.1
Name: pytorch-model-parser
Version: 0.1.0
Summary: A library to parse PyTorch CNN models and retrieve layer details.
Classifier: Programming Language :: Python :: 3
Classifier: License :: OSI Approved :: MIT License
Classifier: Operating System :: OS Independent
License-File: LICENSE
Requires-Dist: torch
Requires-Dist: torchvision
